cc_clients/__init__.py
cc_clients/client_utils/__init__.py
cc_clients/client_utils/cache.py
cc_clients/client_utils/progress.py
cc_clients/clients/__init__.py
cc_clients/clients/base.py
cc_clients/clients/openai/openai.py
cc_clients/clients/openai/utils.py
cc_clients-0.1.0.dist-info/LICENSE
cc_clients-0.1.0.dist-info/METADATA
cc_clients-0.1.0.dist-info/WHEEL
cc_clients-0.1.0.dist-info/top_level.txt
cc_clients-0.1.0.dist-info/RECORD
