Metadata-Version: 2.2
Name: cc-clients
Version: 0.1.0
Summary: Concurrent API clients for various APIs with caching.
Author-email: Lei Zhang <jameszhang2880@gmail.com>
License: MIT
Classifier: Programming Language :: Python :: 3
Classifier: License :: OSI Approved :: MIT License
Classifier: Operating System :: OS Independent
Requires-Python: >=3.9
License-File: LICENSE
Requires-Dist: openai
